README.rst
setup.cfg
setup.py
src/schema2rst/__init__.py
src/schema2rst/rstwriter.py
src/schema2rst.egg-info/PKG-INFO
src/schema2rst.egg-info/SOURCES.txt
src/schema2rst.egg-info/dependency_links.txt
src/schema2rst.egg-info/entry_points.txt
src/schema2rst.egg-info/requires.txt
src/schema2rst.egg-info/top_level.txt
src/schema2rst/commands/__init__.py
src/schema2rst/commands/dump.py
src/schema2rst/commands/graph.py
src/schema2rst/commands/rst.py
src/schema2rst/inspectors/__init__.py
src/schema2rst/inspectors/base.py
src/schema2rst/inspectors/mysql.py
src/schema2rst/inspectors/pgsql.py