Metadata-Version: 1.0
Name: schema2rst
Version: 0.9.0
Summary: schema2rst generates reST doc from database schema
Home-page: https://bitbucket.org/tk0miya/schema2rst
Author: Takeshi Komiya
Author-email: i.tkomiya at gmail.com
License: PSL
Keywords: document,generator
Platform: UNKNOWN
Classifier: Development Status :: 5 - Production/Stable
Classifier: Intended Audience :: Developers
Classifier: License :: OSI Approved :: Python Software Foundation License
Classifier: Programming Language :: Python
Classifier: Topic :: Software Development
Classifier: Topic :: Software Development :: Documentation
